travelpayouts/__init__.py
travelpayouts/client.py
travelpayouts/common.py
travelpayouts/exceptions.py
travelpayouts/flights.py
travelpayouts/v1.py
travelpayouts/v2.py
travelpayouts-1.1.0.dist-info/LICENSE.txt
travelpayouts-1.1.0.dist-info/METADATA
travelpayouts-1.1.0.dist-info/WHEEL
travelpayouts-1.1.0.dist-info/top_level.txt
travelpayouts-1.1.0.dist-info/RECORD
