Metadata-Version: 2.1
Name: travelpayouts
Version: 1.1.0
Summary: Travel Payouts API Wrapper
Home-page: http://github.com/karellens/travelpayouts-python
Author: Denis Bozhenkov
Author-email: mm@karellens.com
License: MIT
Download-URL: https://github.com/karellens/travelpayouts-python/archive/1.1.0.tar.gz
Platform: UNKNOWN
Classifier: Development Status :: 3 - Alpha
Classifier: Intended Audience :: Developers
Classifier: Programming Language :: Python :: 3
Requires-Python: >=3
Requires-Dist: requests
